preact_codegen/__init__.py
preact_codegen/main.py
preact_codegen/prompts.py
preact_codegen-2025.12.21144856.dist-info/METADATA
preact_codegen-2025.12.21144856.dist-info/WHEEL
preact_codegen-2025.12.21144856.dist-info/top_level.txt
preact_codegen-2025.12.21144856.dist-info/RECORD
