Metadata-Version: 2.4
Name: preact-codegen
Version: 2025.12.21144856
Summary: A new package that helps developers quickly set up Preact applications without needing a complex build configuration. Users can describe their application requirements in plain text, including desired
Author-email: preact-codegen <hi@eugene.plus>
License: MIT
Project-URL: Homepage, https://github.com/chigwell/preact-codegen
Requires-Python: >=3.9
Requires-Dist: langchain-llm7>=0.0.0
Requires-Dist: llmatch-messages>=0.0.0
Requires-Dist: langchain-core>=0.3.0
